sbnltk/Bangla_translator.py
sbnltk/Checker.py
sbnltk/Downloader.py
sbnltk/Extractive_Summarizer.py
sbnltk/FBM_Information_Extraction.py
sbnltk/NER.py
sbnltk/Ner_bert.py
sbnltk/Postag.py
sbnltk/Postag_bert.py
sbnltk/Preprocessor.py
sbnltk/Semantic_Information_Extraction.py
sbnltk/Sentence_embedding.py
sbnltk/SentimentAnalyzer.py
sbnltk/Stemmer.py
sbnltk/Tokenizer.py
sbnltk/__init__.py
sbnltk/main.py
sbnltk/sbnltk_default.py
sbnltk/word_embedding.py
sbnltk-1.0.5.dist-info/LICENSE
sbnltk-1.0.5.dist-info/METADATA
sbnltk-1.0.5.dist-info/WHEEL
sbnltk-1.0.5.dist-info/top_level.txt
sbnltk-1.0.5.dist-info/RECORD
