Metadata-Version: 2.1
Name: sbnltk
Version: 1.0.5
Summary: Bangla NLP toolkit
Home-page: https://github.com/Foysal87/sbnltk
Author: Towhid Ahmed Foysal
Author-email: towhidfoysal123@gmail.com
License: MIT
Platform: UNKNOWN
Classifier: License :: OSI Approved :: MIT License
Classifier: Programming Language :: Python :: 3
Requires-Python: >=3.6
License-File: LICENSE
Requires-Dist: gdown (>=3.12.2)
Requires-Dist: google-trans-new (>=1.1.9)
Requires-Dist: transformers (>=4.3.2)
Requires-Dist: torch (>=1.7.1)
Requires-Dist: tensorflow (>=2.4.1)
Requires-Dist: sklearn-crfsuite
Requires-Dist: sentence-transformers
